pymsg.py
pymsg-0.1.3.dist-info/METADATA
pymsg-0.1.3.dist-info/WHEEL
pymsg-0.1.3.dist-info/top_level.txt
pymsg-0.1.3.dist-info/RECORD
