Metadata-Version: 2.1
Name: pymsg
Version: 0.1.3
Summary: UNKNOWN
Home-page: https://github.com/Dog-Egg/pymsg
Author: Lee
Author-email: 294622946@qq.com
License: UNKNOWN
Platform: UNKNOWN
Requires-Dist: requests
